mitchiCalpackage/__init__.py
mitchiCalpackage/add.py
mitchiCalpackage/mitchiCalPackage_example.py
mitchiCalpackage/subtract.py
mitchiCalpackage/extras/__init__.py
mitchiCalpackage/extras/divide.py
mitchiCalpackage/extras/multiply.py
mitchiCalpackage/extras/power.py
mitchiCalpackage-0.0.6.dist-info/METADATA
mitchiCalpackage-0.0.6.dist-info/WHEEL
mitchiCalpackage-0.0.6.dist-info/top_level.txt
mitchiCalpackage-0.0.6.dist-info/RECORD
